{
  "last_update": "2026-06-15T16:13:24.654181",
  "last_update_readable": "2026-06-15 16:13:24",
  "content_hash": "651bb8f0bcb1258373faf32508eccfb3",
  "html_file": "docs/index_a.html",
  "html_file_size": 12391,
  "market_status": "A股市场扫描",
  "update_time": "2026-06-15 15:34:58",
  "mode": "A股市场模式",
  "stats": {
    "total_scanned": 4662,
    "success_count": 4653,
    "signal_count": 19,
    "blacklist_count": 0,
    "stocks_displayed": 151
  },
  "config": {
    "rsi_period": 8,
    "macd_params": "8,17,9"
  }
}