{
  "last_update": "2026-03-03T05:13:46.437175",
  "last_update_readable": "2026-03-03 05:13:46",
  "content_hash": "24363b9fd93bf01ce69ef08524de3791",
  "html_file": "docs/index.html",
  "html_file_size": 15648,
  "market_status": "🌙 盘后时段（缓存缓冲）",
  "update_time": "2026-03-02 16:11:45 EST",
  "mode": "盘前/盘后模式",
  "stats": {
    "total_scanned": 2092,
    "success_count": 2087,
    "signal_count": 1,
    "blacklist_count": 0,
    "stocks_displayed": 2087
  },
  "config": {
    "rsi_period": 8,
    "macd_params": "8,17,9"
  }
}