{
  "last_update": "2026-04-09T15:52:31.001637",
  "last_update_readable": "2026-04-09 15:52:31",
  "content_hash": "06b0958bd65bdb35d6ad1f111729e91a",
  "html_file": "docs/index_a.html",
  "html_file_size": 18250,
  "market_status": "A股市场扫描",
  "update_time": "2026-04-09 15:47:04",
  "mode": "A股市场模式",
  "stats": {
    "total_scanned": 4490,
    "success_count": 4465,
    "signal_count": 7,
    "blacklist_count": 0,
    "stocks_displayed": 403
  },
  "config": {
    "rsi_period": 8,
    "macd_params": "8,17,9"
  }
}