{
  "last_update": "2026-07-18T04:16:10.539139",
  "last_update_readable": "2026-07-18 04:16:10",
  "content_hash": "d11ee3411b9474ba81fbc28c211e3956",
  "html_file": "docs/index.html",
  "html_file_size": 11070,
  "market_status": "🌙 盘后时段（缓存缓冲）",
  "update_time": "2026-07-17 16:14:01 EDT",
  "mode": "盘前/盘后模式",
  "stats": {
    "total_scanned": 2157,
    "success_count": 2150,
    "signal_count": 14,
    "blacklist_count": 0,
    "stocks_displayed": 14
  },
  "config": {
    "rsi_period": 8,
    "macd_params": "8,17,9"
  }
}