{
  "last_update": "2026-02-26T11:53:07.667489",
  "last_update_readable": "2026-02-26 11:53:07",
  "content_hash": "c934a56e9b50a84fa7e5bf618d65e3b0",
  "html_file": "docs/index_a.html",
  "html_file_size": 16757,
  "market_status": "A股市场扫描",
  "update_time": "2026-02-26 11:43:45",
  "mode": "A股市场模式",
  "stats": {
    "total_scanned": 4487,
    "success_count": 4466,
    "signal_count": 5,
    "blacklist_count": 0,
    "stocks_displayed": 4466
  },
  "config": {
    "rsi_period": 8,
    "macd_params": "8,17,9"
  }
}