{
  "last_update": "2026-06-29T10:34:39.964348",
  "last_update_readable": "2026-06-29 10:34:39",
  "content_hash": "c02c14a201a107068a678aaf6b4d6f6c",
  "html_file": "docs/index_a.html",
  "html_file_size": 10628,
  "market_status": "A股市场扫描",
  "update_time": "2026-06-29 09:41:25",
  "mode": "A股市场模式",
  "stats": {
    "total_scanned": 4665,
    "success_count": 4656,
    "signal_count": 12,
    "blacklist_count": 0,
    "stocks_displayed": 240
  },
  "config": {
    "rsi_period": 8,
    "macd_params": "8,17,9"
  }
}