{
  "last_update": "2026-03-12T15:31:27.055432",
  "last_update_readable": "2026-03-12 15:31:27",
  "content_hash": "aeb37ea487d2f8774412aed9f9c49550",
  "html_file": "docs/index_a.html",
  "html_file_size": 59607,
  "market_status": "A股市场扫描",
  "update_time": "2026-03-12 15:17:29",
  "mode": "A股市场模式",
  "stats": {
    "total_scanned": 4487,
    "success_count": 4473,
    "signal_count": 18,
    "blacklist_count": 0,
    "stocks_displayed": 1865
  },
  "config": {
    "rsi_period": 8,
    "macd_params": "8,17,9"
  }
}