{
  "last_update": "2025-11-22T14:22:15.749758",
  "last_update_readable": "2025-11-22 14:22:15",
  "content_hash": "c5fa5ed2dc1a849955e2d6198bb7b819",
  "html_file": "docs/index_hk.html",
  "html_file_size": 6915,
  "market_status": "港股市场扫描",
  "update_time": "2025-11-22 10:37:28",
  "mode": "港股市场模式",
  "stats": {
    "total_scanned": 2680,
    "success_count": 635,
    "signal_count": 0,
    "blacklist_count": 0,
    "stocks_displayed": 635
  },
  "config": {
    "rsi_period": 8,
    "macd_params": "8,17,9"
  },
  "update_history": [
    {
      "timestamp": "2025-11-21T04:44:41.983040",
      "timestamp_readable": "2025-11-21 04:44:41",
      "content_hash": "9e455141e580f025f868e17c2a6a9f56",
      "market_status": "港股市场扫描",
      "stocks_count": 638,
      "signals": 0
    },
    {
      "timestamp": "2025-11-21T08:57:14.012733",
      "timestamp_readable": "2025-11-21 08:57:14",
      "content_hash": "c3ba3718d11b8efbde62021d8fcb47fd",
      "market_status": "港股市场扫描",
      "stocks_count": 636,
      "signals": 0
    },
    {
      "timestamp": "2025-11-22T14:22:15.749758",
      "timestamp_readable": "2025-11-22 14:22:15",
      "content_hash": "c5fa5ed2dc1a849955e2d6198bb7b819",
      "market_status": "港股市场扫描",
      "stocks_count": 635,
      "signals": 0
    }
  ],
  "total_updates": 3
}