{
  "last_update": "2026-02-04T16:31:16.721532",
  "last_update_readable": "2026-02-04 16:31:16",
  "content_hash": "9b45f408bbcda4ac1878197e0db00086",
  "html_file": "docs/index_a.html",
  "html_file_size": 34171,
  "market_status": "A股市场扫描",
  "update_time": "2026-02-04 15:15:20",
  "mode": "A股市场模式",
  "stats": {
    "total_scanned": 4572,
    "success_count": 4486,
    "signal_count": 12,
    "blacklist_count": 0,
    "stocks_displayed": 4486
  },
  "config": {
    "rsi_period": 8,
    "macd_params": "8,17,9"
  }
}