{
  "last_update": "2026-04-10T11:22:40.206433",
  "last_update_readable": "2026-04-10 11:22:40",
  "content_hash": "804d171f0ac480ce854eea64a5378bcc",
  "html_file": "docs/index.html",
  "html_file_size": 9241,
  "market_status": "💤 夜盘时段",
  "update_time": "2026-04-09 23:20:39 EDT",
  "mode": "盘前/盘后模式",
  "stats": {
    "total_scanned": 2113,
    "success_count": 2104,
    "signal_count": 1,
    "blacklist_count": 0,
    "stocks_displayed": 256
  },
  "config": {
    "rsi_period": 8,
    "macd_params": "8,17,9"
  }
}